bg_utils/__init__.py
bg_utils/__version__.py
bg_utils/recommend.py
bg_utils/transformers.py
board_game_utils-0.2.0.dist-info/LICENSE
board_game_utils-0.2.0.dist-info/METADATA
board_game_utils-0.2.0.dist-info/WHEEL
board_game_utils-0.2.0.dist-info/top_level.txt
board_game_utils-0.2.0.dist-info/RECORD
