Metadata-Version: 2.1
Name: board-game-utils
Version: 0.2.0
Summary: Various board game utilities.
Home-page: https://recommend.games/
Author: Markus Shepherd
Author-email: markus@recommend.games
License: MIT
Project-URL: Documentation, https://gitlab.com/recommend.games/board-game-utils/blob/master/README.md
Project-URL: Funding, https://paypal.me/mschepke
Project-URL: Say Thanks!, https://saythanks.io/to/mk.schepke%40gmail.com
Project-URL: Source, https://gitlab.com/recommend.games/board-game-utils
Project-URL: Tracker, https://gitlab.com/recommend.games/board-game-utils/issues
Project-URL: Twitter, https://twitter.com/recommend_games
Keywords: board games,tabletop games,boardgamegeek,bgg
Platform: UNKNOWN
Classifier: License :: OSI Approved :: MIT License
Classifier: Programming Language :: Python
Classifier: Programming Language :: Python :: 3.6
Classifier: Programming Language :: Python :: 3.7
Classifier: Programming Language :: Python :: 3.8
Classifier: Programming Language :: Python :: 3.9
Classifier: Programming Language :: Python :: 3.10
Classifier: Topic :: Games/Entertainment :: Board Games
Requires-Python: >=3.6.0
License-File: LICENSE
Requires-Dist: requests
Provides-Extra: ml
Requires-Dist: numpy ; extra == 'ml'
Requires-Dist: pandas ; extra == 'ml'
Requires-Dist: pytility ; extra == 'ml'
Requires-Dist: scikit-learn ; extra == 'ml'
Requires-Dist: scipy ; extra == 'ml'
